j0xj/__init__.py
j0xj/j.py
j0xj-0.0.2.dist-info/LICENSE
j0xj-0.0.2.dist-info/METADATA
j0xj-0.0.2.dist-info/WHEEL
j0xj-0.0.2.dist-info/top_level.txt
j0xj-0.0.2.dist-info/RECORD
