Metadata-Version: 2.1
Name: j0xj
Version: 0.0.2
Summary: Shortcuts for j
Home-page: UNKNOWN
Author: J0x494949
Author-email: j0x494949@mej.com
License: UNKNOWN
Keywords: python,jmax,j0x494949,jmaxojan,hotkeys,shortcuts
Platform: UNKNOWN
Classifier: Development Status :: 1 - Planning
Classifier: Intended Audience :: Developers
Classifier: Programming Language :: Python :: 3
Classifier: Operating System :: Unix
Classifier: Operating System :: MacOS :: MacOS X
Classifier: Operating System :: Microsoft :: Windows
License-File: LICENSE
